proxyfile/__init__.py
proxyfile/cli.py
proxyfile/core.py
proxyfile/proxylist.py
proxyfile-0.1.0.dist-info/LICENSE
proxyfile-0.1.0.dist-info/METADATA
proxyfile-0.1.0.dist-info/WHEEL
proxyfile-0.1.0.dist-info/entry_points.txt
proxyfile-0.1.0.dist-info/RECORD
