Metadata-Version: 2.3
Name: proxyfile
Version: 0.1.0
Summary: download files through random free proxies
Author: dtDhruv
Author-email: dhruvthanawala10@gmail.com
Requires-Python: >=3.11
Classifier: Programming Language :: Python :: 3
Classifier: Programming Language :: Python :: 3.11
Classifier: Programming Language :: Python :: 3.12
Classifier: Programming Language :: Python :: 3.13
Requires-Dist: requests (>=2.32.4,<3.0.0)
Requires-Dist: tqdm (>=4.67.1,<5.0.0)
